{
  "timestamp": "July 14, 2026 — 01:37 AM NY Time",
  "timestamp_iso": "2026-07-14T01:37:40.459677-04:00",
  "rates": {
    "USDCNY": 6.7792,
    "EURCNY": 7.7251,
    "GBPCNY": 9.0634
  },
  "prices": {
    "brent": {
      "price": 84.258,
      "change": "+1.15%",
      "unit": "/bbl"
    },
    "wti": {
      "price": 79.106,
      "change": "+1.24%",
      "unit": "/bbl"
    },
    "en590": {
      "price": 765.0,
      "change": "0.00%",
      "unit": "/MT"
    },
    "sulphur": {
      "price": 1332.852,
      "change": "+1.69%",
      "unit": "/MT"
    },
    "urea": {
      "price": 415.5,
      "change": "+7.23%",
      "unit": "/MT"
    },
    "npk": {
      "price": 349.0,
      "change": "0.00%",
      "unit": "/MT"
    },
    "jet": {
      "price": 841.0,
      "change": "0.00%",
      "unit": "/MT"
    },
    "mazut": {
      "price": 318.0,
      "change": "0.00%",
      "unit": "/MT"
    },
    "natgas": {
      "price": 2.8778,
      "change": "-0.66%",
      "unit": "/MMBtu"
    },
    "bitumen": {
      "price": 598.4482,
      "change": "+2.35%",
      "unit": "/MT"
    },
    "aluminum": {
      "price": 3155.65,
      "change": "+0.30%",
      "unit": "/T"
    },
    "nickel": {
      "price": 16844.0,
      "change": "+0.62%",
      "unit": "/T"
    },
    "gold": {
      "price": 4030.05,
      "change": "+0.71%",
      "unit": "/t.oz"
    },
    "silver": {
      "price": 58.201,
      "change": "+1.01%",
      "unit": "/t.oz"
    },
    "copper": {
      "price": 6.331,
      "change": "+1.57%",
      "unit": "/Lbs"
    },
    "molybdenum": {
      "price": 90.3499,
      "change": "0.00%",
      "unit": "/Kg"
    },
    "polypropylene": {
      "price": 1149.6932,
      "change": "+1.64%",
      "unit": "/T"
    },
    "urals": {
      "price": 53.71,
      "change": "-2.56%",
      "unit": "/bbl"
    }
  }
}