{
  "timestamp": "July 02, 2026 — 11:32 AM NY Time",
  "timestamp_iso": "2026-07-02T11:32:29.675441-04:00",
  "rates": {
    "USDCNY": 6.7873,
    "EURCNY": 7.7678,
    "GBPCNY": 9.0716
  },
  "prices": {
    "brent": {
      "price": 70.641,
      "change": "-1.30%",
      "unit": "/bbl"
    },
    "wti": {
      "price": 67.614,
      "change": "-1.41%",
      "unit": "/bbl"
    },
    "en590": {
      "price": 641.0,
      "change": "0.00%",
      "unit": "/MT"
    },
    "sulphur": {
      "price": 1336.172,
      "change": "+0.74%",
      "unit": "/MT"
    },
    "urea": {
      "price": 362.5,
      "change": "-1.49%",
      "unit": "/MT"
    },
    "npk": {
      "price": 292.0,
      "change": "0.00%",
      "unit": "/MT"
    },
    "jet": {
      "price": 705.0,
      "change": "0.00%",
      "unit": "/MT"
    },
    "mazut": {
      "price": 266.0,
      "change": "0.00%",
      "unit": "/MT"
    },
    "natgas": {
      "price": 3.1912,
      "change": "-0.89%",
      "unit": "/MMBtu"
    },
    "bitumen": {
      "price": 559.7218,
      "change": "+0.08%",
      "unit": "/MT"
    },
    "aluminum": {
      "price": 3090.4,
      "change": "-0.22%",
      "unit": "/T"
    },
    "nickel": {
      "price": 16263.0,
      "change": "-0.78%",
      "unit": "/T"
    },
    "gold": {
      "price": 4125.84,
      "change": "+2.34%",
      "unit": "/t.oz"
    },
    "silver": {
      "price": 61.199,
      "change": "+3.58%",
      "unit": "/t.oz"
    },
    "copper": {
      "price": 6.1338,
      "change": "+0.17%",
      "unit": "/Lbs"
    },
    "molybdenum": {
      "price": 88.7687,
      "change": "0.00%",
      "unit": "/Kg"
    },
    "polypropylene": {
      "price": 1056.6794,
      "change": "-1.39%",
      "unit": "/T"
    },
    "urals": {
      "price": 56.19,
      "change": "-4.67%",
      "unit": "/bbl"
    }
  }
}